alibabacloud_cms20190101/__init__.py
alibabacloud_cms20190101/client.py
alibabacloud_cms20190101/models/__init__.py
alibabacloud_cms20190101/models/_add_tags_request.py
alibabacloud_cms20190101/models/_add_tags_response.py
alibabacloud_cms20190101/models/_add_tags_response_body.py
alibabacloud_cms20190101/models/_alert_event.py
alibabacloud_cms20190101/models/_alert_strategy_relation.py
alibabacloud_cms20190101/models/_apply_metric_rule_template_request.py
alibabacloud_cms20190101/models/_apply_metric_rule_template_response.py
alibabacloud_cms20190101/models/_apply_metric_rule_template_response_body.py
alibabacloud_cms20190101/models/_batch_create_instant_site_monitor_request.py
alibabacloud_cms20190101/models/_batch_create_instant_site_monitor_response.py
alibabacloud_cms20190101/models/_batch_create_instant_site_monitor_response_body.py
alibabacloud_cms20190101/models/_batch_export_request.py
alibabacloud_cms20190101/models/_batch_export_response.py
alibabacloud_cms20190101/models/_batch_export_response_body.py
alibabacloud_cms20190101/models/_batch_export_shrink_request.py
alibabacloud_cms20190101/models/_create_dynamic_tag_group_request.py
alibabacloud_cms20190101/models/_create_dynamic_tag_group_response.py
alibabacloud_cms20190101/models/_create_dynamic_tag_group_response_body.py
alibabacloud_cms20190101/models/_create_group_metric_rules_request.py
alibabacloud_cms20190101/models/_create_group_metric_rules_response.py
alibabacloud_cms20190101/models/_create_group_metric_rules_response_body.py
alibabacloud_cms20190101/models/_create_group_monitoring_agent_process_request.py
alibabacloud_cms20190101/models/_create_group_monitoring_agent_process_response.py
alibabacloud_cms20190101/models/_create_group_monitoring_agent_process_response_body.py
alibabacloud_cms20190101/models/_create_host_availability_request.py
alibabacloud_cms20190101/models/_create_host_availability_response.py
alibabacloud_cms20190101/models/_create_host_availability_response_body.py
alibabacloud_cms20190101-4.0.8.dist-info/LICENSE
alibabacloud_cms20190101-4.0.8.dist-info/METADATA
alibabacloud_cms20190101-4.0.8.dist-info/WHEEL
alibabacloud_cms20190101-4.0.8.dist-info/top_level.txt
alibabacloud_cms20190101-4.0.8.dist-info/RECORD
